CHANGES.txt
LICENSE.txt
MANIFEST.in
README.rst
setup.py
aiopg/__init__.py
aiopg/connection.py
aiopg/cursor.py
aiopg/log.py
aiopg/pool.py
aiopg/sa/__init__.py
aiopg/sa/connection.py
aiopg/sa/engine.py
aiopg/sa/exc.py
aiopg/sa/result.py
aiopg/sa/transaction.py
aiopgx.egg-info/PKG-INFO
aiopgx.egg-info/SOURCES.txt
aiopgx.egg-info/dependency_links.txt
aiopgx.egg-info/requires.txt
aiopgx.egg-info/top_level.txt