Metadata-Version: 1.1
Name: aiopgx
Version: 0.7.0
Summary: Postgres integration with asyncio.
Home-page: http://aiopg.readthedocs.org
Author: Andrew Svetlov
Author-email: andrew.svetlov@gmail.com
License: BSD
Download-URL: https://pypi.python.org/pypi/aiopg
Platform: POSIX
Classifier: License :: OSI Approved :: BSD License
Classifier: Intended Audience :: Developers
Classifier: Programming Language :: Python :: 3
Classifier: Programming Language :: Python :: 3.3
Classifier: Programming Language :: Python :: 3.4
Classifier: Operating System :: POSIX
Classifier: Operating System :: MacOS :: MacOS X
Classifier: Environment :: Web Environment
Classifier: Development Status :: 4 - Beta
Classifier: Topic :: Database
Classifier: Topic :: Database :: Front-Ends
Requires: psycopg2
Provides: aiopg
